{
  "bead_id": "B-83f9c770",
  "title": "Document Installation And Project Onboarding",
  "agent_type": "documentation",
  "description": "Add user-facing documentation covering package installation, the interactive init workflow, generated project layout, and project-specific customization of templates and skills.",
  "status": "ready",
  "bead_type": "task",
  "parent_id": "B-031382d2",
  "dependencies": [
    "B-68f905b7"
  ],
  "acceptance_criteria": [
    "Docs explain `uv tool install` and `pip install` usage for the packaged CLI.",
    "Docs describe `orchestrator init`, its prompts, and the files/directories it creates.",
    "Docs explain that projects own their copied templates and skills after initialization and can customize them locally."
  ],
  "linked_docs": [
    "spec-5db8d0ec"
  ],
  "feature_root_id": "B-031382d2",
  "execution_branch_name": "feature/b-031382d2",
  "execution_worktree_path": "/Users/oscar.renalias/Projects/codex-agent-orchestration/.orchestrator/worktrees/B-031382d2",
  "expected_files": [
    "docs/onboarding.md",
    "src/codex_orchestrator/cli.py"
  ],
  "expected_globs": [
    "docs/**/*.md",
    "src/codex_orchestrator/*.py"
  ],
  "touched_files": [
    "src/codex_orchestrator/cli.py"
  ],
  "changed_files": [
    "src/codex_orchestrator/cli.py"
  ],
  "updated_docs": [],
  "handoff_summary": {
    "completed": "",
    "remaining": "",
    "risks": "",
    "verdict": "",
    "findings_count": 0,
    "requires_followup": false,
    "changed_files": [],
    "updated_docs": [],
    "next_action": "",
    "next_agent": "",
    "block_reason": "",
    "expected_files": [],
    "expected_globs": [],
    "touched_files": [],
    "conflict_risks": ""
  },
  "block_reason": "",
  "conflict_risks": "None. Only cli.py was touched; no overlap with other in-progress beads expected.",
  "branch_name": "",
  "worktree_path": "",
  "lease": null,
  "retries": 0,
  "execution_history": [
    {
      "timestamp": "2026-04-05T11:53:10.973396+00:00",
      "event": "created",
      "agent_type": "scheduler",
      "summary": "Bead created",
      "details": {}
    }
  ],
  "metadata": {}
}
