{
  "bead_id": "B-8d48e734-docs",
  "title": "Document Align onboarding known-issues matching with canonical stack names",
  "agent_type": "documentation",
  "description": "Update docs for B-8d48e734",
  "status": "ready",
  "bead_type": "task",
  "parent_id": "B-8d48e734",
  "dependencies": [
    "B-8d48e734"
  ],
  "acceptance_criteria": [],
  "linked_docs": [
    "spec-302156c2"
  ],
  "feature_root_id": "B-2b9df640",
  "execution_branch_name": "feature/b-2b9df640",
  "execution_worktree_path": "/Users/oscar.renalias/Projects/codex-agent-orchestration/.takt/worktrees/B-2b9df640",
  "expected_files": [
    "src/agent_takt/onboarding/scaffold.py",
    "tests/test_onboarding_prompts.py"
  ],
  "expected_globs": [],
  "touched_files": [
    "src/agent_takt/onboarding/scaffold.py",
    "tests/test_onboarding_prompts.py"
  ],
  "changed_files": [
    "src/agent_takt/onboarding/scaffold.py",
    "tests/test_onboarding_prompts.py"
  ],
  "updated_docs": [],
  "handoff_summary": {
    "completed": "",
    "remaining": "",
    "risks": "",
    "verdict": "",
    "findings_count": 0,
    "requires_followup": false,
    "changed_files": [],
    "updated_docs": [],
    "next_action": "",
    "next_agent": "",
    "block_reason": "",
    "expected_files": [],
    "expected_globs": [],
    "touched_files": [],
    "conflict_risks": "",
    "design_decisions": "",
    "test_coverage_notes": "",
    "known_limitations": ""
  },
  "block_reason": "file-scope conflict with in-progress B-8d48e734-test",
  "conflict_risks": "None \u2014 only `scaffold.py` was modified; no overlap with other in-progress beads.",
  "branch_name": "",
  "worktree_path": "",
  "lease": null,
  "retries": 0,
  "execution_history": [
    {
      "timestamp": "2026-04-12T19:58:32.330196+00:00",
      "event": "created",
      "agent_type": "scheduler",
      "summary": "Bead created",
      "details": {}
    },
    {
      "timestamp": "2026-04-12T19:58:34.010386+00:00",
      "event": "deferred",
      "agent_type": "documentation",
      "summary": "file-scope conflict with in-progress B-8d48e734-test",
      "details": {}
    }
  ],
  "metadata": {},
  "labels": [],
  "recovery_for": null,
  "priority": null
}
