{
  "bead_id": "B-dc079adb-review",
  "title": "Review Resolve merge conflicts for Feature Root: Rename project to agent-takt",
  "agent_type": "review",
  "description": "Review implementation for B-dc079adb",
  "status": "ready",
  "bead_type": "task",
  "parent_id": "B-dc079adb",
  "dependencies": [
    "B-dc079adb",
    "B-dc079adb-docs"
  ],
  "acceptance_criteria": [],
  "linked_docs": [],
  "feature_root_id": "B-80cd72ce",
  "execution_branch_name": "feature/b-80cd72ce",
  "execution_worktree_path": "/Users/oscar.renalias/Projects/codex-agent-orchestration/.takt/worktrees/B-80cd72ce",
  "expected_files": [
    ".takt/beads/B-dc079adb.json",
    "uv.lock"
  ],
  "expected_globs": [],
  "touched_files": [
    ".takt/beads/B-dc079adb.json",
    "uv.lock"
  ],
  "changed_files": [
    ".takt/beads/B-dc079adb.json",
    "uv.lock"
  ],
  "updated_docs": [],
  "handoff_summary": {
    "completed": "",
    "remaining": "",
    "risks": "",
    "verdict": "",
    "findings_count": 0,
    "requires_followup": false,
    "changed_files": [],
    "updated_docs": [],
    "next_action": "",
    "next_agent": "",
    "block_reason": "",
    "expected_files": [],
    "expected_globs": [],
    "touched_files": [],
    "conflict_risks": "",
    "design_decisions": "",
    "test_coverage_notes": "",
    "known_limitations": ""
  },
  "block_reason": "",
  "conflict_risks": "None \u2014 uv.lock conflict resolved, file is clean",
  "branch_name": "",
  "worktree_path": "",
  "lease": null,
  "retries": 0,
  "execution_history": [
    {
      "timestamp": "2026-04-06T16:59:59.506295+00:00",
      "event": "created",
      "agent_type": "scheduler",
      "summary": "Bead created",
      "details": {}
    }
  ],
  "metadata": {}
}
